single_chars_counter_package/__init__.py
single_chars_counter_package/single_chars_counter.py
single_chars_counter_package-0.0.2.dist-info/METADATA
single_chars_counter_package-0.0.2.dist-info/WHEEL
single_chars_counter_package-0.0.2.dist-info/licenses/LICENSE.txt
single_chars_counter_package-0.0.2.dist-info/RECORD
